{
  "hadith": {
    "hadith_id": 2349,
    "narrator": "ফাযালা ইবনু উবাইদ (রাঃ)",
    "bn": "তিনি রাসূলুল্লাহ (সাল্লাল্লাহু ‘আলাইহি ওয়া সাল্লাম)-কে বলতে শুনেছেন : সেই ব্যক্তি কতই না সৌভাগ্যবান যাকে ইসলামের পথে হিদায়াত দান করা হয়েছে এবং তার জীবিকা ন্যূনতম প্রয়োজন মাফিক এবং সে তাতেই খুশি।\n\nসহীহ্‌ , তা’লীকুর রাগীব (২/১১), সহীহাহ্ (১৫০৬)।",
    "ar": "حَدَّثَنَا الْعَبَّاسُ بْنُ مُحَمَّدٍ الدُّورِيُّ، حَدَّثَنَا عَبْدُ اللَّهِ بْنُ يَزِيدَ الْمُقْرِئُ، أَخْبَرَنَا حَيْوَةُ بْنُ شُرَيْحٍ، أَخْبَرَنِي أَبُو هَانِئٍ الْخَوْلاَنِيُّ، أَنَّ أَبَا عَلِيٍّ، عَمْرَو بْنَ مَالِكٍ الْجَنْبِيَّ أَخْبَرَهُ عَنْ فَضَالَةَ بْنِ عُبَيْدٍ، أَنَّهُ سَمِعَ رَسُولَ اللَّهِ صلى الله عليه وسلم يَقُولُ ‏ \"‏ طُوبَى لِمَنْ هُدِيَ إِلَى الإِسْلاَمِ وَكَانَ عَيْشُهُ كَفَافًا وَقَنِعَ ‏\"‏ ‏.‏ قَالَ وَأَبُو هَانِئٍ اسْمُهُ حُمَيْدُ بْنُ هَانِئٍ ‏.‏ قَالَ أَبُو عِيسَى هَذَا حَدِيثٌ حَسَنٌ صَحِيحٌ ‏.‏",
    "grade_id": 2,
    "grade": "সহিহ হাদিস",
    "grade_color": "#46B891",
    "note": "আবূ হানীর নাম হুমাইদ ইবনু হানী। আবূ ঈসা বলেন, এ হাদীসটি হাসান সহীহ্।",
    "chapter": {
      "chapter_number": "34"
    }
  }
}