{
  "hadith": {
    "hadith_id": 2744,
    "narrator": "উমার ইবনু ইসহাক ইবনু আবূ তালহা (রহঃ)এর নানা",
    "bn": "রাসূলুল্লাহ (সাল্লাল্লাহু ‘আলাইহি ওয়া সাল্লাম) বলেছেনঃ তিনবার পর্যন্ত হাঁচির উত্তর দাও। এরপরও সে যদি হাঁচি দেয় তবে তুমি চাইলে তার উত্তর দিতেও পার নাও দিতে পার। \n\nযঈফ, যঈফা (৪৮৩০), আবূ ঈসা বলেন, এ হাদীসটি গারীব এবং এর সনদসূত্র অপরিচিত।",
    "ar": "حَدَّثَنَا الْقَاسِمُ بْنُ دِينَارٍ الْكُوفِيُّ، حَدَّثَنَا إِسْحَاقُ بْنُ مَنْصُورٍ السَّلُولِيُّ الْكُوفِيُّ، عَنْ عَبْدِ السَّلاَمِ بْنِ حَرْبٍ، عَنْ يَزِيدَ بْنِ عَبْدِ الرَّحْمَنِ أَبِي خَالِدٍ الدَّالاَنِيِّ، عَنْ عُمَرَ بْنِ إِسْحَاقَ بْنِ أَبِي طَلْحَةَ، عَنْ أُمِّهِ، عَنْ أَبِيهَا، قَالَ قَالَ رَسُولُ اللَّهِ صلى الله عليه وسلم ‏ \"‏ يُشَمَّتُ الْعَاطِسُ ثَلاَثًا فَإِنْ زَادَ فَإِنْ شِئْتَ فَشَمِّتْهُ وَإِنْ شِئْتَ فَلاَ ‏\"‏ ‏.‏ قَالَ أَبُو عِيسَى هَذَا حَدِيثٌ غَرِيبٌ وَإِسْنَادُهُ مَجْهُولٌ ‏.‏",
    "grade_id": 4,
    "grade": "দুর্বল হাদিস",
    "grade_color": "#F85B24",
    "note": null,
    "chapter": {
      "chapter_number": "41"
    }
  }
}