{
  "hadith": {
    "hadith_id": 1055,
    "narrator": "আবু হুরায়রাহ্ (রাঃ)",
    "bn": "রসূলুল্লাহ (সাল্লাল্লাহু ‘আলাইহি ওয়া সাল্লাম) বলেছেন। আমাকে সংক্ষিপ্ত অথচ ব্যাপক অর্থবোধক কথা বলার ক্ষমতা দেয়া হয়েছে। আমাকে অত্যন্ত প্রভাব দ্বারা সাহায্য করা হয়েছে। একদিন ঘুমের মাঝে স্বপ্নে আমার কাছে পৃথিবীর ধনভান্ডারের চাবিসমূহ এনে আমার হাতে দেয়া হলো। আবু হুরায়রাহ্...... (এর ব্যাখ্যা করে) বলেছেন। রসূলুল্লাহ (সাল্লাল্লাহু ‘আলাইহি ওয়া সাল্লাম) তো বিদায় নিয়ে চলে গিয়েছেন, আর তোমরা তা আহরণ [১] করে চলেছ। (ই. ফা. ১০৪৯ ই. সে. ১০৫৮)",
    "ar": "حَدَّثَنِي أَبُو الطَّاهِرِ، وَحَرْمَلَةُ، قَالاَ أَخْبَرَنَا ابْنُ وَهْبٍ، حَدَّثَنِي يُونُسُ، عَنِ ابْنِ شِهَابٍ، عَنْ سَعِيدِ بْنِ الْمُسَيَّبِ، عَنْ أَبِي هُرَيْرَةَ، قَالَ قَالَ رَسُولُ اللَّهِ صلى الله عليه وسلم ‏ \"‏ بُعِثْتُ بِجَوَامِعِ الْكَلِمِ وَنُصِرْتُ بِالرُّعْبِ وَبَيْنَا أَنَا نَائِمٌ أُتِيتُ بِمَفَاتِيحِ خَزَائِنِ الأَرْضِ فَوُضِعَتْ فِي يَدَىَّ ‏\"‏ ‏.‏ قَالَ أَبُو هُرَيْرَةَ فَذَهَبَ رَسُولُ اللَّهِ صلى الله عليه وسلم وَأَنْتُمْ تَنْتَثِلُونَهَا ‏.",
    "grade_id": 2,
    "grade": "সহিহ হাদিস",
    "grade_color": "#46B891",
    "note": "[১] দুনিয়ার দিক-দিগন্ত বিজিত হওয়া এবং ধনরাজী আহরণ  করা। (শারহে নাবাবী – ১ম খন্ড, ১৯৯)",
    "chapter": {
      "chapter_number": "5"
    }
  }
}