{
  "hadith": {
    "hadith_id": 1513,
    "narrator": "'আবদুল্লাহ ইবনু 'আব্বাস (রাঃ)",
    "bn": "তিনি বলেন, রসূলুল্লাহ্‌ (সাল্লাল্লাহু ‘আলাইহি ওয়া সাল্লাম) ভীতিকর অবস্থা কিংবা সফররত অবস্থা ছাড়াই এবং 'আস্‌রের সলাত একসাথে এবং মাগরিব ও 'ইশার সলাত একসাথে আদায় করেছেন। (ই.ফা. ১৪৯৮, ই.সে. ১৫০৭)",
    "ar": "حَدَّثَنَا يَحْيَى بْنُ يَحْيَى، قَالَ قَرَأْتُ عَلَى مَالِكٍ عَنْ أَبِي الزُّبَيْرِ، عَنْ سَعِيدِ بْنِ جُبَيْرٍ، عَنِ ابْنِ عَبَّاسٍ، قَالَ صَلَّى رَسُولُ اللَّهِ صلى الله عليه وسلم الظُّهْرَ وَالْعَصْرَ جَمِيعًا وَالْمَغْرِبَ وَالْعِشَاءَ جَمِيعًا فِي غَيْرِ خَوْفٍ وَلاَ سَفَرٍ ‏.",
    "grade_id": 2,
    "grade": "সহিহ হাদিস",
    "grade_color": "#46B891",
    "note": null,
    "chapter": {
      "chapter_number": "6"
    }
  }
}