{
  "hadith": {
    "hadith_id": 1683,
    "narrator": "‘আবদুল্লাহ ইবনু ‘আব্বাস (রাঃ)",
    "bn": "তিনি বলেন, আমি একরাতে আমার খালা [নবী (সাল্লাল্লাহু ‘আলাইহি ওয়া সাল্লাম) এর স্ত্রী] মায়মূনাহ্-এর ঘরে ঘুমালেন। উক্ত রাতে নবী (সাল্লাল্লাহু ‘আলাইহি ওয়া সাল্লাম) রাতে কিভাবে সলাত আদায় করেন তা দেখা ছিল আমার উদ্দেশ্য। 'আবদুল্লাহ ইবনু 'আব্বাস বলেছেনঃ তিনি তাঁর স্ত্রীর সাথে কিছুক্ষন কথাবার্তা বললেন এবং তারপর ঘুমিয়ে পড়লেন। .......এতটুকু বলার পর পূর্ব বর্ণিত হাদীসের অনুরূপ বর্ণনা করেন। তবে এতে এতটুকু কথা অধিক আছে যে, তিনি উঠে ওযূ ও মিসওয়াক করলেন। (ই.ফা. ১৬৬৮, ই.সে. ১৬৭৫)",
    "ar": "وَحَدَّثَنِي أَبُو بَكْرِ بْنُ إِسْحَاقَ، أَخْبَرَنَا ابْنُ أَبِي مَرْيَمَ، أَخْبَرَنَا مُحَمَّدُ بْنُ جَعْفَرٍ، أَخْبَرَنِي شَرِيكُ بْنُ أَبِي نَمِرٍ، عَنْ كُرَيْبٍ، عَنِ ابْنِ عَبَّاسٍ، أَنَّهُ قَالَ رَقَدْتُ فِي بَيْتِ مَيْمُونَةَ لَيْلَةَ كَانَ النَّبِيُّ صلى الله عليه وسلم عِنْدَهَا لأَنْظُرَ كَيْفَ صَلاَةُ النَّبِيِّ صلى الله عليه وسلم بِاللَّيْلِ - قَالَ - فَتَحَدَّثَ النَّبِيُّ صلى الله عليه وسلم مَعَ أَهْلِهِ سَاعَةً ثُمَّ رَقَدَ ‏.‏ وَسَاقَ الْحَدِيثَ وَفِيهِ ثُمَّ قَامَ فَتَوَضَّأَ وَاسْتَنَّ ‏.‏",
    "grade_id": 2,
    "grade": "সহিহ হাদিস",
    "grade_color": "#46B891",
    "note": null,
    "chapter": {
      "chapter_number": "6"
    }
  }
}