{
  "hadith": {
    "hadith_id": 3815,
    "narrator": "জাবির ইবনু ‘আবদুল্লাহ (রা.)",
    "bn": "রসূলুল্লাহ (সাল্লাল্লাহু ‘আলাইহি ওয়া সাল্লাম) বলেছেনঃ  যার নিকট অতিরিক্ত জমি আছে তার উচিত সেটি চাষাবাদ করা অথবা আবাদ করার জন্যে তার অপর ভাইকে দেয়া। তোমরা সেটা বিক্রি করো না।\n(রাবী বলেন) আমি সা’ঈদকে জিজ্ঞেস করলাম, বিক্রি করো না-এ কথা কি বর্গা দেয়া? তিনি বললেন, হ্যাঁ, তা-ই। (ই.ফা. ৩৭৭৯, ই.সে. ৩৭৭৯)",
    "ar": "وَحَدَّثَنِي حَجَّاجُ بْنُ الشَّاعِرِ، حَدَّثَنَا عُبَيْدُ اللَّهِ بْنُ عَبْدِ الْمَجِيدِ، حَدَّثَنَا سَلِيمُ بْنُ، حَيَّانَ حَدَّثَنَا سَعِيدُ بْنُ مِينَاءَ، قَالَ سَمِعْتُ جَابِرَ بْنَ عَبْدِ اللَّهِ، يَقُولُ إِنَّ رَسُولَ اللَّهِ صلى الله عليه وسلم قَالَ ‏ \"‏ مَنْ كَانَ لَهُ فَضْلُ أَرْضٍ فَلْيَزْرَعْهَا أَوْ لِيُزْرِعْهَا أَخَاهُ وَلاَ تَبِيعُوهَا ‏\"‏ ‏.‏ فَقُلْتُ لِسَعِيدٍ مَا قَوْلُهُ وَلاَ تَبِيعُوهَا يَعْنِي الْكِرَاءَ ‏.‏ قَالَ نَعَمْ ‏.‏",
    "grade_id": 2,
    "grade": "সহিহ হাদিস",
    "grade_color": "#46B891",
    "note": null,
    "chapter": {
      "chapter_number": "22"
    }
  }
}