{
  "hadith": {
    "hadith_id": 4456,
    "narrator": "ইবনু ‘উমার (রাঃ)",
    "bn": "তিনি বলেন, রসূলুল্লাহ (সাল্লাল্লাহু ‘আলাইহি ওয়াসাল্লাম) ক্ষুদ্র সেনাদলের মাঝে যুদ্ধলব্ধ মালামাল বন্টণের ব্যাপারে ইবনু ‘উমার থেকে আমার নিকট ইবনু রাজা কতৃক বর্ণিত হাদীসের মতো একটি হাদীস এসেছে। ( ই.ফা. ৪৪১৪, ই.সে. ৪৪১৪)",
    "ar": "وَحَدَّثَنَا هَنَّادُ بْنُ السَّرِيِّ، حَدَّثَنَا ابْنُ الْمُبَارَكِ، ح وَحَدَّثَنِي حَرْمَلَةُ بْنُ يَحْيَى، أَخْبَرَنَا ابْنُ وَهْبٍ، كِلاَهُمَا عَنْ يُونُسَ، عَنِ ابْنِ شِهَابٍ، قَالَ بَلَغَنِي عَنِ ابْنِ عُمَرَ، قَالَ نَفَّلَ رَسُولُ اللَّهِ صلى الله عليه وسلم سَرِيَّةً بِنَحْوِ حَدِيثِ ابْنِ رَجَاءٍ ‏.‏",
    "grade_id": 2,
    "grade": "সহিহ হাদিস",
    "grade_color": "#46B891",
    "note": null,
    "chapter": {
      "chapter_number": "33"
    }
  }
}