{
  "hadith": {
    "hadith_id": 6701,
    "narrator": "আবূ হুরাইরাহ্ (রাঃ)",
    "bn": "তিনি বলেন, একবার রসূলুল্লাহ (সাল্লাল্লাহু ‘আলাইহি ওয়া সাল্লাম) মক্কার পথে চলতে থাকেন। অতঃপর ‘জুমদন’ নামে একটি পর্বতের কাছে গেলেন। এরপর তিনি বললেন, তোমরা এ জমদান পর্বতে সফর করো। ‘মুফার্রিদ’গণ অগ্রগামী হয়েছে। মানুষেরা প্রশ্ন করল, ‘মুফার্রিদ’ কারা! হে আল্লাহর রসূল (সাল্লাল্লাহু ‘আলাইহি ওয়া সাল্লাম)? তিনি বললেন, বেশি বেশি আল্লাহর যিকিরে নিয়োজিত পুরুষ ও নারী। (ই.ফা. ৬৫৬৪, ই.সে. ৬৬১৮)",
    "ar": "حَدَّثَنَا أُمَيَّةُ بْنُ بِسْطَامَ الْعَيْشِيُّ، حَدَّثَنَا يَزِيدُ، - يَعْنِي ابْنَ زُرَيْعٍ - حَدَّثَنَا رَوْحُ، بْنُ الْقَاسِمِ عَنِ الْعَلاَءِ، عَنْ أَبِيهِ، عَنْ أَبِي هُرَيْرَةَ، قَالَ كَانَ رَسُولُ اللَّهِ صلى الله عليه وسلم يَسِيرُ فِي طَرِيقِ مَكَّةَ فَمَرَّ عَلَى جَبَلٍ يُقَالُ لَهُ جُمْدَانُ فَقَالَ ‏\"‏ سِيرُوا هَذَا جُمْدَانُ سَبَقَ الْمُفَرِّدُونَ ‏\"‏ ‏.‏ قَالُوا وَمَا الْمُفَرِّدُونَ يَا رَسُولَ اللَّهِ قَالَ ‏\"‏ الذَّاكِرُونَ اللَّهَ كَثِيرًا وَالذَّاكِرَاتُ ‏\"‏ ‏.‏",
    "grade_id": 2,
    "grade": "সহিহ হাদিস",
    "grade_color": "#46B891",
    "note": null,
    "chapter": {
      "chapter_number": "49"
    }
  }
}