{
  "hadith": {
    "hadith_id": 7094,
    "narrator": "আবূ হুরাইরাহ্ (রাঃ)-এর সূত্রে নাবী (সাল্লাল্লাহু ‘আলাইহি ওয়া সাল্লাম)",
    "bn": "তিনি বলেন, লোকদেরকে তিন শ্রেণীতে ভাগ করে সমবেত করা হবে। প্রথম দল আশা পোষণকারী এবং ভীত-সন্ত্রস্ত লোকদের দল। দ্বিতীয় দলে সেসব লোক যাদের দু’জন থাকবে এক উটের উপর, কোন উটের উপর তিনজন, কোনটির উপর চারজন, আর কোনটির উপরে আরোহিত হবে দশজন। অবশিষ্টরা হবে সে সকল লোক যাদেরকে আগুন তাড়িয়ে নিয়ে যাবে। তারা যেখানে রাত্রিযাপন করবে আগুনও তাদের সঙ্গে রাত কাটাবে। তারা যেখানে বিশ্রাম নিবে আগুনও সেখানে বিশ্রাম নিবে। তাদের যেখানে সকাল হবে আগুনও তাদের সঙ্গে থাকবে। আর যেখানে তাদের সন্ধ্যা হবে একই সঙ্গে আগুনও তাদের সাথে থাকবে। (ই.ফা. ৬৯৩৮, ই.সে. ৬৯৯৬)",
    "ar": "",
    "grade_id": 2,
    "grade": "সহিহ হাদিস",
    "grade_color": "#46B891",
    "note": null,
    "chapter": {
      "chapter_number": "53"
    }
  }
}