{
  "hadith": {
    "hadith_id": 948,
    "narrator": "আনাস (রাঃ)",
    "bn": "তিনি বলেন, আমি রসূলুল্লাহ (সাল্লাল্লাহু ‘আলাইহি ওয়া সাল্লাম) এর পিছনে যেরূপ সংক্ষিপ্ত ও পূর্ণাঙ্গ সলাত  আদায় করেছি অনুরূপ আর কারো পিছনে আদায় করিনি। রসূলুল্লাহ (সাল্লাল্লাহু ‘আলাইহি ওয়া সাল্লাম) এর সলাতের  (রুকনগুলোর সময়ের) পরিমাণ প্রায় কাছকাছি ছিল। আবূ বকর (রাঃ) -এর সলাতের  (রুকনগুলোও) পরস্পর কাছকাছি ছিল। ‘উমার ইবনুল খাত্তাব তাঁর সময়ে ফযরের সলাত  দীর্ঘ করে দেন। রসূলুল্লাহ (সাল্লাল্লাহু ‘আলাইহি ওয়া সাল্লাম)  যখন “সামি’আল্লা-হু লিমান হামিদাহ” বলে দাঁড়িয়ে যেতেন -এমনকি আমরা (মনে মনে) বলতাম, তিনি (সাজদায় যেতে) ভুলে গেছেন। অতঃপর তিনি সাজদায় যেতেন।  দু’সাজদার মাঝখানে  তিনি এতক্ষণ বসতেন যে, আমরা (মনে মনে) বলতাম, তিনি (পরবর্তী সিজদায় যেতে) ভুলে গেছেন। (ই.ফা. ৯৪৩, ই.সে. ৯৫৪)",
    "ar": "وَحَدَّثَنِي أَبُو بَكْرِ بْنُ نَافِعٍ الْعَبْدِيُّ، حَدَّثَنَا بَهْزٌ، حَدَّثَنَا حَمَّادٌ، أَخْبَرَنَا ثَابِتٌ، عَنْ أَنَسٍ، قَالَ مَا صَلَّيْتُ خَلْفَ أَحَدٍ أَوْجَزَ صَلاَةً مِنْ صَلاَةِ رَسُولِ اللَّهِ صلى الله عليه وسلم فِي تَمَامٍ كَانَتْ صَلاَةُ رَسُولِ اللَّهِ صلى الله عليه وسلم مُتَقَارِبَةً وَكَانَتْ صَلاَةُ أَبِي بَكْرٍ مُتَقَارِبَةً فَلَمَّا كَانَ عُمَرُ بْنُ الْخَطَّابِ مَدَّ فِي صَلاَةِ الْفَجْرِ وَكَانَ رَسُولُ اللَّهِ صلى الله عليه وسلم إِذَا قَالَ ‏ \"‏ سَمِعَ اللَّهُ لِمَنْ حَمِدَهُ ‏\"‏ ‏.‏ قَامَ حَتَّى نَقُولَ قَدْ أَوْهَمَ ‏.‏ ثُمَّ يَسْجُدُ وَيَقْعُدُ بَيْنَ السَّجْدَتَيْنِ حَتَّى نَقُولَ قَدْ أَوْهَمَ ‏.‏",
    "grade_id": 2,
    "grade": "সহিহ হাদিস",
    "grade_color": "#46B891",
    "note": null,
    "chapter": {
      "chapter_number": "4"
    }
  }
}