{
  "hadith": {
    "hadith_id": 2927,
    "narrator": "সাইদ (রহঃ)",
    "bn": "তিনি বলেন, ‘উমার ইবনুল খাত্তাব (রাঃ) বলতেন, রক্তপণে বংশের লোকদের অংশ আছে। স্ত্রী তার স্বামীর দিয়াতের ওয়ারিস হয় না। দাহ্‌হাক ইবনু সুফিয়ান (রাঃ) তাকে বললেন, রাসূলুল্লাহ (সাল্লাল্লাহু ‘আলাইহি ওয়া সাল্লাম) আমাকে লিখিত নির্দেশ পাঠান : আশ’আম আদ-দিবাবীর স্ত্রীকে তার রক্তপণের ওয়ারিস বানাও। তখন ‘উমার (রাঃ) নিজস্ব মত পরিবর্তন করেন। অন্য বর্ণনায় আছে, নবী (সাল্লাল্লাহু ‘আলাইহি ওয়া সাল্লাম) তাকে বেদুঈনদের প্রশাসক নিযুক্ত করেন।",
    "ar": "حَدَّثَنَا أَحْمَدُ بْنُ صَالِحٍ، حَدَّثَنَا سُفْيَانُ، عَنِ الزُّهْرِيِّ، عَنْ سَعِيدٍ، قَالَ كَانَ عُمَرُ بْنُ الْخَطَّابِ يَقُولُ الدِّيَةُ لِلْعَاقِلَةِ وَلاَ تَرِثُ الْمَرْأَةُ مِنْ دِيَةِ زَوْجِهَا شَيْئًا حَتَّى قَالَ لَهُ الضَّحَّاكُ بْنُ سُفْيَانَ كَتَبَ إِلَىَّ رَسُولُ اللَّهِ صلى الله عليه وسلم أَنْ أُوَرِّثَ امْرَأَةَ أَشْيَمَ الضِّبَابِيِّ مِنْ دِيَةِ زَوْجِهَا ‏.‏ فَرَجَعَ عُمَرُ ‏.‏ قَالَ أَحْمَدُ بْنُ صَالِحٍ حَدَّثَنَا عَبْدُ الرَّزَّاقِ بِهَذَا الْحَدِيثِ عَنْ مَعْمَرٍ عَنِ الزُّهْرِيِّ عَنْ سَعِيدٍ وَقَالَ فِيهِ وَكَانَ النَّبِيُّ صلى الله عليه وسلم اسْتَعْمَلَهُ عَلَى الأَعْرَابِ ‏.‏",
    "grade_id": 2,
    "grade": "সহিহ হাদিস",
    "grade_color": "#46B891",
    "note": null,
    "chapter": {
      "chapter_number": "19"
    }
  }
}