{
  "hadith": {
    "hadith_id": 344,
    "narrator": "‘আবদুর রহমান ইবনু আবূ সাঈদ আল-খুদরী (রাঃ) থেকে তার পিতা",
    "bn": "নবী (সাল্লাল্লাহু ‘আলাইহি ওয়া সাল্লাম) বলেছেনঃ প্রত্যেক প্রাপ্তবয়স্ক ব্যক্তির উপর জুমু’আহ্‌র দিন গোসল করা, মিসওয়াক করা এবং সাধ্যানুযায়ী সুগন্ধি ব্যবহার করা কর্তব্য। কিন্তু বুকাইর সানাদে ‘আবদুর রহমানের নাম উল্লেখ করেননি এবং বর্ণনাকারী সুগন্ধি সম্পর্কে বলেছেন, যদিও তা মহিলাদের সুগন্ধি হয়। \n\nসহীহঃ মুসলিম, অনুরূপ বুখারী।",
    "ar": "حَدَّثَنَا مُحَمَّدُ بْنُ سَلَمَةَ الْمُرَادِيُّ، حَدَّثَنَا ابْنُ وَهْبٍ، عَنْ عَمْرِو بْنِ الْحَارِثِ، أَنَّ سَعِيدَ بْنَ أَبِي هِلاَلٍ، وَبُكَيْرَ بْنَ عَبْدِ اللَّهِ بْنِ الأَشَجِّ، حَدَّثَاهُ عَنْ أَبِي بَكْرِ بْنِ الْمُنْكَدِرِ، عَنْ عَمْرِو بْنِ سُلَيْمٍ الزُّرَقِيِّ، عَنْ عَبْدِ الرَّحْمَنِ بْنِ أَبِي سَعِيدٍ الْخُدْرِيِّ، عَنْ أَبِيهِ، أَنَّ رَسُولَ اللَّهِ صلى الله عليه وسلم قَالَ ‏\"‏ الْغُسْلُ يَوْمَ الْجُمُعَةِ عَلَى كُلِّ مُحْتَلِمٍ وَالسِّوَاكُ وَيَمَسُّ مِنَ الطِّيبِ مَا قُدِّرَ لَهُ ‏\"‏ ‏.‏ إِلاَّ أَنَّ بُكَيْرًا لَمْ يَذْكُرْ عَبْدَ الرَّحْمَنِ وَقَالَ فِي الطِّيبِ ‏\"‏ وَلَوْ مِنْ طِيبِ الْمَرْأَةِ ‏\"‏ ‏.‏",
    "grade_id": 2,
    "grade": "সহিহ হাদিস",
    "grade_color": "#46B891",
    "note": null,
    "chapter": {
      "chapter_number": "1"
    }
  }
}