{
  "hadith": {
    "hadith_id": 1973,
    "narrator": "আয়িশা (রাঃ)",
    "bn": "কোন কারণে রাসুলুল্লাহ (সাল্লাল্লাহু ‘আলাইহি ওয়া সাল্লাম) সাফিয়্যা বিনতু হুয়াই (রাঃ) এর উপর অসন্তুষ্ট হলে তিনি (সাফিয়্যা) বলেন, হে আয়িশা! তুমি কি রাসুলুল্লাহ (সাল্লাল্লাহু ‘আলাইহি ওয়া সাল্লাম) কে আমার প্রতি সন্তুষ্ট করে দিবে?  আমি আমার পালার দিনটি তোমাকে দিবো। আয়িশা (রাঃ) বলেন, হ্যাঁ। এরপর তিনি যাফরান রংয়ে রঞ্জিত তার একটি ওড়না নিলেন এবং তাতে পানি ছিটিয়ে দিলেন, যাতে এর ঘ্রাণ ছড়িয়ে পড়ে। অতঃপর তিনি রাসুলুল্লাহ (সাল্লাল্লাহু ‘আলাইহি ওয়া সাল্লাম) এর পাশে বসলে তিনি বলেনঃ হে আয়িশা! তুমি আমার নিকট থেকে সরে যাও। এটা তোমার পালার দিন নয়। আয়িশা (রাঃ) বলেন, এটি হচ্ছে আল্লাহর অনুগ্রহ যাকে ইচ্ছা তিনি দান করেন। তিনি তাঁকে ব্যাপারটি খুলে বলেন। তাতে রাসুলুল্লাহ (সাল্লাল্লাহু ‘আলাইহি ওয়া সাল্লাম) সাফিয়্যা (রাঃ) এর প্রতি সন্তুষ্ট হয়ে যান। [১৯৭৩]",
    "ar": "حَدَّثَنَا أَبُو بَكْرِ بْنُ أَبِي شَيْبَةَ وَمُحَمَّدُ بْنُ يَحْيَى قَالَا حَدَّثَنَا عَفَّانُ حَدَّثَنَا حَمَّادُ بْنُ سَلَمَةَ عَنْ ثَابِتٍ عَنْ سُمَيَّةَ عَنْ عَائِشَةَ أَنَّ رَسُولَ اللهِ صلى الله عليه وسلم وَجَدَ عَلَى صَفِيَّةَ بِنْتِ حُيَيٍّ فِي شَيْءٍ فَقَالَتْ صَفِيَّةُ يَا عَائِشَةُ هَلْ لَكِ أَنْ تُرْضِي رَسُولَ اللهِ صلى الله عليه وسلم عَنِّي وَلَكِ يَوْمِي قَالَتْ نَعَمْ فَأَخَذَتْ خِمَارًا لَهَا مَصْبُوغًا بِزَعْفَرَانٍ فَرَشَّتْهُ بِالْمَاءِ لِيَفُوحَ رِيحُهُ ثُمَّ قَعَدَتْ إِلَى جَنْبِ رَسُولُ اللَّه صلى الله عليه وسلم فَقَالَ النَّبِيُّ صلى الله عليه وسلم يَا عَائِشَةُ إِلَيْكِ عَنِّي إِنَّهُ لَيْسَ يَوْمَكِ فَقَالَتْ ذَلِكَ فَضْلُ اللهِ يُؤْتِيهِ مَنْ يَشَاءُ فَأَخْبَرَتْهُ بِالْأَمْرِ فَرَضِيَ عَنْهَا",
    "grade_id": 4,
    "grade": "দুর্বল হাদিস",
    "grade_color": "#F85B24",
    "note": "[১৯৭৩] হাদিসটি ইমাম ইবনু মাজাহ এককভাবে বর্ণনা করেছেন। ইরওয়াহ ৭/৮৫। তাহকীক আলবানীঃ যঈফ।",
    "chapter": {
      "chapter_number": "9"
    }
  }
}