{
  "hadith": {
    "hadith_id": 3180,
    "narrator": "আবূ হুরায়রাহ (রাঃ)",
    "bn": "রাসূলুল্লাহ (সাল্লাল্লাহু ‘আলাইহি ওয়া সাল্লাম) এক আনসার ব্যক্তির নিকট এলেন। সে রাসূলুল্লাহ (সাল্লাল্লাহু ‘আলাইহি ওয়া সাল্লাম) এর জন্য পশু যবেহ করতে ছুরি নিলো। রাসূলুল্লাহ (সাল্লাল্লাহু ‘আলাইহি ওয়া সাল্লাম) তাকে বলেনঃ সাবধান! দুগ্ধবতী পশু যবেহ করো না। [৩৭৮০]",
    "ar": "حَدَّثَنَا أَبُو بَكْرِ بْنُ أَبِي شَيْبَةَ، حَدَّثَنَا خَلَفُ بْنُ خَلِيفَةَ، ح وَحَدَّثَنَا عَبْدُ الرَّحْمَنِ بْنُ إِبْرَاهِيمَ، أَنْبَأَنَا مَرْوَانُ بْنُ مُعَاوِيَةَ، جَمِيعًا عَنْ يَزِيدَ بْنِ كَيْسَانَ، عَنْ أَبِي حَازِمٍ، عَنْ أَبِي هُرَيْرَةَ، أَنَّ رَسُولَ اللَّهِ ـ صلى الله عليه وسلم ـ أَتَى رَجُلاً مِنَ الأَنْصَارِ فَأَخَذَ الشَّفْرَةَ لِيَذْبَحَ لِرَسُولِ اللَّهِ ـ صلى الله عليه وسلم ـ فَقَالَ لَهُ رَسُولُ اللَّهِ ـ صلى الله عليه وسلم ـ ‏ \"‏ إِيَّاكَ وَالْحَلُوبَ ‏\"‏ ‏.‏",
    "grade_id": 2,
    "grade": "সহিহ হাদিস",
    "grade_color": "#46B891",
    "note": "[৩১৮০] মুসলিম ২০৩৮, তিরমিযী ২৩৬৯, যইফাহ ৪৭১৯ নং হাদিসের অনুরূপ। তাহকীক আলবানীঃ সহীহ। উক্ত হাদিসের রাবী খালফ বিন খালিফাহ সম্পর্কে আবু আহমাদ বিন আদী আল-জুরজানী বলেন, আমি আশা করি তার মাঝে কোন সমস্যা নেই। তিনি কিছু কিছু রেওয়ায়াতে ভুল করেছেন। আবু হাতিম আর-রাযী বলেন, তিনি সত্যবাদী। ইবনু হাজার আল-আসকালানী বলেন, তিনি সত্যবাদী তবে শেষ বয়সে হাদিস বর্ণনায় সংমিশ্রণ করেছেন। ইমাম যাহাবী বলেন, তিনি সত্যবাদী। (তাহযীবুল কামালঃ রাবী নং ১৭০৭, ৮/২৮৪ নং পৃষ্ঠা) ২. ইয়াযীদ বিন কায়সান সম্পর্কে আবু আহমাদ আল-হাকিম বলেন, তিনি আহলে ইলমের নিকট হাফিয নয়। আবু আহমাদ বিন আদী আল-জুরজানী বলেন, আমি আশা করি তার হাদিস বর্ণনায় কোন সমস্যা নেই। আহমাদ বিন শু'আয়ব আন-নাসায়ী বলেন, তিনি সিকাহ। ইবনু হাজার আল-আসকালানী বলেন, তিনি সত্যবাদী তবে হাদিস বর্ণনায় ভুল করেন। (তাহযীবুল কামালঃ রাবী নং ৭০৪১, ৩২/৩২০ নং পৃষ্ঠা)",
    "chapter": {
      "chapter_number": "27"
    }
  }
}