{
  "hadith": {
    "hadith_id": 354,
    "narrator": "আয়িশাহ (রাঃ)",
    "bn": "তিনি বলেন, আমি দেখেছি যে, রসূলুল্লাহ (সাল্লাল্লাহু ‘আলাইহি ওয়া সাল্লাম) কখনো পানি ব্যবহার না করে পায়খানা থেকে বের হননি। [৩৫২]",
    "ar": "حَدَّثَنَا هَنَّادُ بْنُ السَّرِيِّ، حَدَّثَنَا أَبُو الأَحْوَصِ، عَنْ مَنْصُورٍ، عَنْ إِبْرَاهِيمَ، عَنِ الأَسْوَدِ، عَنْ عَائِشَةَ، قَالَتْ مَا رَأَيْتُ رَسُولَ اللَّهِ ـ صلى الله عليه وسلم ـ خَرَجَ مِنْ غَائِطٍ قَطُّ إِلاَّ مَسَّ مَاءً ‏.‏",
    "grade_id": 2,
    "grade": "সহিহ হাদিস",
    "grade_color": "#46B891",
    "note": "[৩৫২] তিরমিযী ১৯, নাসায়ী ৪৬, আহমাদ ২৪১১৮, ২৪৩১৫, ২৪৩৬৯, ২৪৪৬৩। তাহক্বীক্ব আলবানী: সহীহ।",
    "chapter": {
      "chapter_number": "1"
    }
  }
}