{
  "hadith": {
    "hadith_id": 4246,
    "narrator": "আবূ হুরায়রাহ (রাঃ)",
    "bn": "নবী (সাল্লাল্লাহু ‘আলাইহি ওয়া সাল্লাম) কে জিজ্ঞেস করা হলো, কোন্‌ জিনিসের বদৌলতে বেশিরভাগ লোক জান্নাতে প্রবেশ করবে। তিনি বলেনঃ তাক্বওয়া ও সচ্চরিত্রের বদৌলতে। তাকে আরও জিজ্ঞেস করা হলো, কোন্‌ জিনিসের কারণে অধিকাংশ লোক জাহান্নামে যাবে? তিনি বলেনঃ দু’টি অংগ- মুখ ও লজ্জাস্থান। [৩৫৭৮]\n\nতাহকীক আলবানীঃ সহীহ।",
    "ar": "حَدَّثَنَا هَارُونُ بْنُ إِسْحَاقَ، وَعَبْدُ اللَّهِ بْنُ سَعِيدٍ، قَالاَ حَدَّثَنَا عَبْدُ اللَّهِ بْنُ إِدْرِيسَ، عَنْ أَبِيهِ، وَعَمِّهِ، عَنْ جَدِّهِ، عَنْ أَبِي هُرَيْرَةَ، قَالَ ‏:‏ سُئِلَ النَّبِيُّ ـ صلى الله عليه وسلم ـ ‏:‏ مَا أَكْثَرُ مَا يُدْخِلُ الْجَنَّةَ قَالَ ‏:‏ ‏\"‏ التَّقْوَى وَحُسْنُ الْخُلُقِ ‏\"‏ ‏.‏ وَسُئِلَ ‏:‏ مَا أَكْثَرُ مَا يُدْخِلُ النَّارَ قَالَ ‏:‏ ‏\"‏ الأَجْوَفَانِ ‏:‏ الْفَمُ وَالْفَرْجُ ‏\"‏ ‏.‏",
    "grade_id": 2,
    "grade": "সহিহ হাদিস",
    "grade_color": "#46B891",
    "note": "[৩৫৭৮] আহ্মাদ ৭৮৪৭, ৮৮৫২, ৯৪০৩। সহিহাহ ৯৭৭।",
    "chapter": {
      "chapter_number": "37"
    }
  }
}