{
  "hadith": {
    "hadith_id": 821,
    "narrator": "ইবনু আব্বাস (রাঃ)",
    "bn": "তিনি বলেন, রসূলুল্লাহ (সাল্লাল্লাহু ‘আলাইহি ওয়া সাল্লাম) জুমুআহর দিন ফজরের সলাতে সূরা আলিফ-লাম-মিম তানযীল আস-সাজদা এবং হাল আতা আলাল ইনসানে  (সূরা আদ-দাহর) তিলাওয়াত করতেন। [৮১৯]",
    "ar": "حَدَّثَنَا أَبُو بَكْرِ بْنُ خَلاَّدٍ الْبَاهِلِيُّ، حَدَّثَنَا وَكِيعٌ، وَعَبْدُ الرَّحْمَنِ بْنُ مَهْدِيٍّ، قَالاَ حَدَّثَنَا سُفْيَانُ، عَنْ مُخَوَّلٍ، عَنْ مُسْلِمٍ الْبَطِينِ، عَنْ سَعِيدِ بْنِ جُبَيْرٍ، عَنِ ابْنِ عَبَّاسٍ، قَالَ كَانَ رَسُولُ اللَّهِ ـ صلى الله عليه وسلم ـ يَقْرَأُ فِي صَلاَةِ الصُّبْحِ يَوْمَ الْجُمُعَةِ ‏{الم * تَنْزِيلُ }‏ وَ ‏{هَلْ أَتَى عَلَى الإِنْسَانِ}‏",
    "grade_id": 2,
    "grade": "সহিহ হাদিস",
    "grade_color": "#46B891",
    "note": "[৮১৯] মুসলিম ৮৭৯, তিরমিযী ৫২০, সা ৯৫৬, ১৪২১; আবূ দাঊদ ১০৭৪, আহমাদ ১৯৯৪, ২৪৫২, ২৭৯৬, ৩০৩১, ৩০৮৬, ৩১৫০, ৩৩১৫। তাহক্বীক্ব আলবানী: সহীহ। তাখরীজ আলবানী: ইরওয়াহ ৯৫, সহীহ আবূ দাউদ ৯৮৫।",
    "chapter": {
      "chapter_number": "5"
    }
  }
}