{
  "hadith": {
    "hadith_id": 1031,
    "narrator": "আনাস ইব্‌নু মালিক (রাঃ)",
    "bn": "তিনি বলেন, নবী (সাল্লাল্লাহু ‘আলাইহি ওয়া সাল্লাম) ইসতিস্‌কা ছাড়া অন্য কোথাও দু’আর মধ্যে হাত উঠাতেন না। তিনি হাত এতটুকু উপরে উঠাতেন যে, তাঁর বগলের শুভ্রতা দেখা যেত।",
    "ar": "حَدَّثَنَا مُحَمَّدُ بْنُ بَشَّارٍ، حَدَّثَنَا يَحْيَى، وَابْنُ أَبِي عَدِيٍّ، عَنْ سَعِيدٍ، عَنْ قَتَادَةَ، عَنْ أَنَسِ بْنِ مَالِكٍ، قَالَ كَانَ النَّبِيُّ صلى الله عليه وسلم لاَ يَرْفَعُ يَدَيْهِ فِي شَىْءٍ مِنْ دُعَائِهِ إِلاَّ فِي الاِسْتِسْقَاءِ، وَإِنَّهُ يَرْفَعُ حَتَّى يُرَى بَيَاضُ إِبْطَيْهِ‏.‏",
    "grade_id": 2,
    "grade": "সহিহ হাদিস",
    "grade_color": "#46B891",
    "note": null,
    "chapter": {
      "chapter_number": "15"
    }
  }
}