{
  "hadith": {
    "hadith_id": 3212,
    "narrator": "সা’ঈদ ইব্‌নু মুসাইয়্যাব (রহঃ)",
    "bn": "তিনি বলেন, একদা ‘উমর (রাঃ) মসজিদে নববীতে আগমন করেন, তখন হাস্‌সান ইব্‌নু সাবিত (রাঃ) কবিতা আবৃত্তি করছিলেন। তখন তিনি বললেন, এখানে আপনার চেয়ে উত্তম ব্যক্তির উপস্থিতিতেও আমি কবিতা আবৃত্তি করতাম। অতঃপর তিনি আবূ হুরায়রা (রাঃ)-এর দিকে তাকালেন এবং বললেন, আমি আপনাকে আল্লাহর কসম দিয়ে জিজ্ঞেস করছি; আপনি কি আল্লাহর রসূল (সাল্লাল্লাহু ‘আলাইহি ওয়া সাল্লাম)-কে বলতে শুনেছেন যে, “তুমি আমার পক্ষ হতে জবাব দাও। হে আল্লাহ! আপনি তাকে রুহুল কুদুস [জিবরাঈল (‘আঃ)] দ্বারা সাহায্য করুন।” তিনি উত্তরে বললেন, হ্যাঁ।",
    "ar": "حَدَّثَنَا عَلِيُّ بْنُ عَبْدِ اللَّهِ، حَدَّثَنَا سُفْيَانُ، حَدَّثَنَا الزُّهْرِيُّ، عَنْ سَعِيدِ بْنِ الْمُسَيَّبِ، قَالَ مَرَّ عُمَرُ فِي الْمَسْجِدِ وَحَسَّانُ يُنْشِدُ، فَقَالَ كُنْتُ أُنْشِدُ فِيهِ، وَفِيهِ مَنْ هُوَ خَيْرٌ مِنْكَ، ثُمَّ الْتَفَتَ إِلَى أَبِي هُرَيْرَةَ، فَقَالَ أَنْشُدُكَ بِاللَّهِ، أَسَمِعْتَ رَسُولَ اللَّهِ صلى الله عليه وسلم يَقُولُ ‏ \"‏ أَجِبْ عَنِّي، اللَّهُمَّ أَيِّدْهُ بِرُوحِ الْقُدُسِ ‏\"‏‏.‏ قَالَ نَعَمْ‏.‏",
    "grade_id": 2,
    "grade": "সহিহ হাদিস",
    "grade_color": "#46B891",
    "note": "[১] মসজিদে কবিতা আবৃত্তি করতে হাস্‌সান ইবন সাবিত (রা.)-এর প্রতি উমর (রা.) আপত্তি করাতে তিনি আবু হুরায়রা (রা.)-কে সাক্ষী হিসাবে পেশ করলেন যে, তিনি রাসূলুল্লাহ (সা.)-এর উপস্থিতিতে মসজিদে কবিতা আবৃত্তি করেছেন ।",
    "chapter": {
      "chapter_number": "59"
    }
  }
}