{
  "hadith": {
    "hadith_id": 3353,
    "narrator": "আবূ হুরায়রা (রাঃ)",
    "bn": "তিনি বলেন, হে আল্লাহর রাসূল! মানুষের মাঝে সবচেয়ে সন্মানিত ব্যক্তি কে? তিনি বললেন, তাদের মধ্যে যে সবচেয়ে অধিক মুত্তাকী। তখন তারা বলল, আমরা তো আপনাকে এ ব্যাপারে জিজ্ঞেস করিনি। তিনি বললেন, তা হলে আল্লাহর নবী‎ ইউসূফ, যিনি আল্লাহর নবী‎’র পুত্র, আল্লাহর নবী‎’র পৌত্র এবং আল্লাহর খলীল-এর প্রপৌত্র। তারা বলল, আমরা আপনাকে এ ব্যাপারেও জিজ্ঞেস করিনি। তিনি বললেন, তা হলে কি তোমরা আরবের মূল্যবান গোত্রসমূহের সম্বন্ধে জিজ্ঞেস করেছ? জাহিলী যুগে তাদের মধ্যে যারা সর্বোত্তম ব্যক্তি ছিলেন, ইসলামেও তাঁরা সর্বোত্তম ব্যক্তি যদি তাঁরা ইসলাম সম্পর্কিত জ্ঞানার্জন করেন। আবূ উসামা ও মু’তামির (রহঃ) ................. আবূ হুরায়রা (রাঃ) সূত্রে নবী‎ (সাল্লাল্লাহু ‘আলাইহি ওয়া সাল্লাম) হতে বর্ণিত।",
    "ar": "حَدَّثَنَا عَلِيُّ بْنُ عَبْدِ اللَّهِ، حَدَّثَنَا يَحْيَى بْنُ سَعِيدٍ، حَدَّثَنَا عُبَيْدُ اللَّهِ، قَالَ حَدَّثَنِي سَعِيدُ بْنُ أَبِي سَعِيدٍ، عَنْ أَبِيهِ، عَنْ أَبِي هُرَيْرَةَ ـ رضى الله عنه قِيلَ يَا رَسُولَ اللَّهِ، مَنْ أَكْرَمُ النَّاسِ قَالَ ‏\"‏ أَتْقَاهُمْ ‏\"‏‏.‏ فَقَالُوا لَيْسَ عَنْ هَذَا نَسْأَلُكَ‏.‏ قَالَ ‏\"‏ فَيُوسُفُ نَبِيُّ اللَّهِ ابْنُ نَبِيِّ اللَّهِ ابْنِ نَبِيِّ اللَّهِ ابْنِ خَلِيلِ اللَّهِ ‏\"‏‏.‏ قَالُوا لَيْسَ عَنْ هَذَا نَسْأَلُكَ‏.‏ قَالَ ‏\"‏ فَعَنْ مَعَادِنِ الْعَرَبِ تَسْأَلُونَ خِيَارُهُمْ فِي الْجَاهِلِيَّةِ خِيَارُهُمْ فِي الإِسْلاَمِ إِذَا فَقُهُوا ‏\"‏‏.‏ قَالَ أَبُو أُسَامَةَ وَمُعْتَمِرٌ عَنْ عُبَيْدِ اللَّهِ عَنْ سَعِيدٍ عَنْ أَبِي هُرَيْرَةَ عَنِ النَّبِيِّ صلى الله عليه وسلم‏.‏",
    "grade_id": 2,
    "grade": "সহিহ হাদিস",
    "grade_color": "#46B891",
    "note": null,
    "chapter": {
      "chapter_number": "60"
    }
  }
}