{
  "hadith": {
    "hadith_id": 4055,
    "narrator": "সা’দ ইবনু আবূ ওয়াক্কাস (রাঃ)",
    "bn": "তিনি বলেন, উহূদের দিন নবী (সাল্লাল্লাহু ‘আলাইহি ওয়া সাল্লাম) আমার জন্য তাঁর তীরাধার খুলে দিয়ে বললেন, তোমার জন্য আমার মাতা-পিতা কুরবান হোক; তুমি তীর চালাতে থাক। [৩৭২৫] (আ.প্র. ৩৭৫৩, ই.ফা. ৩৭৫৬)",
    "ar": "عَبْدُ اللهِ بْنُ مُحَمَّدٍ حَدَّثَنَا مَرْوَانُ بْنُ مُعَاوِيَةَ حَدَّثَنَا هَاشِمُ بْنُ هَاشِمٍ السَّعْدِيُّ قَالَ سَمِعْتُ سَعِيْدَ بْنَ الْمُسَيَّبِ يَقُوْلُ سَمِعْتُ سَعْدَ بْنَ أَبِيْ وَقَّاصٍ يَقُوْلُ نَثَلَ لِي النَّبِيُّ صلى الله عليه وسلم كِنَانَتَهُ يَوْمَ أُحُدٍ فَقَالَ ارْمِ فِدَاكَ أَبِيْ وَأُمِّي",
    "grade_id": 2,
    "grade": "সহিহ হাদিস",
    "grade_color": "#46B891",
    "note": null,
    "chapter": {
      "chapter_number": "64"
    }
  }
}