{
  "hadith": {
    "hadith_id": 5809,
    "narrator": "আনাস ইবনু মালিক (রাঃ)",
    "bn": "তিনি বলেন, আমি রসূলুল্লাহ্‌ (সাল্লাল্লাহু ‘আলাইহি ওয়া সাল্লাম) -এর সঙ্গে চলছিলাম। এ সময় তাঁর পরনে চওড়া পাড়ওয়ালা একটি নাজরানী ডোরাদার চাদর ছিল। একজন বেদুঈন তাঁর কাছে এলো। সে তাঁর চাদর ধরে খুব জোরে টান দিল। এমন কি আমি দেখতে পেলাম রসূলুল্লাহ্‌ (সাল্লাল্লাহু ‘আলাইহি ওয়া সাল্লাম) -এর কাঁধে চাদরের পাড়ের দাগ পড়ে গেছে। তারপর সে বললঃ হে মুহাম্মাদ (সাল্লাল্লাহু ‘আলাইহি ওয়া সাল্লাম)! আপনার নিকট আল্লাহ্‌র যে সম্পদ আছে, তা থেকে আমাকে কিছু দিতে বলুন। রসূলুল্লাহ্‌ (সাল্লাল্লাহু ‘আলাইহি ওয়া সাল্লাম) তার দিকে ফিরে তাকিয়ে হাসলেন এবং তাকে কিছু দান করার নির্দেশ দিলেন।(আধুনিক প্রকাশনী- ৫৩৮৪, ইসলামিক ফাউন্ডেশন- ৫২৮০)",
    "ar": "إِسْمَاعِيلُ بْنُ عَبْدِ اللهِ قَالَ حَدَّثَنِي مَالِكٌ عَنْ إِسْحَاقَ بْنِ عَبْدِ اللهِ بْنِ أَبِي طَلْحَةَ عَنْ أَنَسِ بْنِ مَالِكٍ قَالَ كُنْتُ أَمْشِي مَعَ رَسُوْلِ اللهِ صلى الله عليه وسلم وَعَلَيْهِ بُرْدٌ نَجْرَانِيٌّ غَلِيظُ الْحَاشِيَةِ فَأَدْرَكَه“ أَعْرَابِيٌّ فَجَبَذَه“ بِرِدَائِه„ جَبْذَةً شَدِيدَةً حَتّٰى نَظَرْتُ إِلٰى صَفْحَةِ عَاتِقِ رَسُوْلِ اللهِ صلى الله عليه وسلم قَدْ أَثَّرَتْ بِهَا حَاشِيَةُ الْبُرْدِ مِنْ شِدَّةِ جَبْذَتِه„ ثُمَّ قَالَ يَا مُحَمَّدُ مُرْ لِي مِنْ مَالِ اللهِ الَّذِي عِنْدَكَ فَالْتَفَتَ إِلَيْهِ رَسُوْلُ اللهِ صلى الله عليه وسلم ثُمَّ ضَحِكَ ثُمَّ أَمَرَ لَه“ بِعَطَاءٍ.",
    "grade_id": 2,
    "grade": "সহিহ হাদিস",
    "grade_color": "#46B891",
    "note": null,
    "chapter": {
      "chapter_number": "77"
    }
  }
}