{
  "hadith": {
    "hadith_id": 5859,
    "narrator": "আওনের পিতা (ওয়াহ্‌ব ইবনু ‘আবদুল্লাহ) (রাঃ)",
    "bn": "তিনি বলেনঃ আমি নবী (সাল্লাল্লাহু ‘আলাইহি ওয়া সাল্লাম) -এর কাছে এলাম। তখন তিনি একটি লাল রঙের চামড়ার তাঁবুতে ছিলেন। আর বিলালকে দেখলাম তিনি নবী (সাল্লাল্লাহু ‘আলাইহি ওয়া সাল্লাম) -এর অযুর পানি উঠিয়ে দিচ্ছেন এবং লোকজন অযুর পানি নেয়ার জন্য দৌড়াদৌড়ি করছে। যে তাথেকে কিছু পায়, সে তা মেখে নেয়। আর যে সেখান হতে কিছু পায় না, সে তার সাথীর ভিজা হাত হতে কিছু গ্রহণ করে। (আধুনিক প্রকাশনী- ৫৪৩৩, ইসলামিক ফাউন্ডেশন- ৫৩২৯)",
    "ar": "مُحَمَّدُ بْنُ عَرْعَرَةَ قَالَ حَدَّثَنِي عُمَرُ بْنُ أَبِي زَائِدَةَ عَنْ عَوْنِ بْنِ أَبِي جُحَيْفَةَ عَنْ أَبِيهِ قَالَ أَتَيْتُ النَّبِيَّ صلى الله عليه وسلم وَهُوَ فِي قُبَّةٍ حَمْرَاءَ مِنْ أَدَمٍ وَرَأَيْتُ بِلاَلاً أَخَذَ وَضُوءَ النَّبِيِّ صلى الله عليه وسلم وَالنَّاسُ يَبْتَدِرُونَ الْوَضُوءَ فَمَنْ أَصَابَ مِنْه“ شَيْئًا تَمَسَّحَ بِه„ وَمَنْ لَمْ يُصِبْ مِنْه“ شَيْئًا أَخَذَ مِنْ بَلَلِ يَدِ صَاحِبِهِ.",
    "grade_id": 2,
    "grade": "সহিহ হাদিস",
    "grade_color": "#46B891",
    "note": null,
    "chapter": {
      "chapter_number": "77"
    }
  }
}