{
  "hadith": {
    "hadith_id": 6910,
    "narrator": "আবূ হুরাইরাহ্‌ (রাঃ)",
    "bn": "তিনি বলেন, হুযায়ল গোত্রের দু'জন মহিলা ঝগড়াকালে একে অন্যের প্রতি পাথর ছুঁড়ে মারে এবং একজন অন্য জনের গর্ভস্থিত সন্তানকে হত্যা করে ফেলল। তারপর তারা নবী (সাল্লাল্লাহু ‘আলাইহি ওয়া সাল্লাম) - এর কাছে বিচার নিয়ে এল। তিনি ফায়সালা দিলেন যে, ভ্রুনের দিয়াত হল একটি গোলাম অথবা বাঁদী আর এ ফায়সালাও দিলেন যে, নিহত মহিলার দিয়াত হত্যাকারিণীর আসাবার উপর আসবে। (আধুনিক প্রকাশনী- ৬৪৩০, ইসলামিক ফাউন্ডেশন- ৬৪৪২)",
    "ar": "أَحْمَدُ بْنُ صَالِحٍ حَدَّثَنَا ابْنُ وَهْبٍ حَدَّثَنَا يُونُسُ عَنْ ابْنِ شِهَابٍ عَنْ ابْنِ الْمُسَيَّبِ وَأَبِي سَلَمَةَ بْنِ عَبْدِ الرَّحْمٰنِ أَنَّ أَبَا هُرَيْرَةَ قَالَ اقْتَتَلَتْ امْرَأَتَانِ مِنْ هُذَيْلٍ فَرَمَتْ إِحْدَاهُمَا الْأُخْرَى بِحَجَرٍ فَقَتَلَتْهَا وَمَا فِي بَطْنِهَا فَاخْتَصَمُوا إِلَى النَّبِيِّ صلى الله عليه وسلم فَقَضَى أَنَّ دِيَةَ جَنِينِهَا غُرَّةٌ عَبْدٌ أَوْ وَلِيدَةٌ وَقَضَى أَنَّ دِيَةَ الْمَرْأَةِ عَلَى عَاقِلَتِهَا",
    "grade_id": 2,
    "grade": "সহিহ হাদিস",
    "grade_color": "#46B891",
    "note": null,
    "chapter": {
      "chapter_number": "87"
    }
  }
}