{
  "hadith": {
    "hadith_id": 1738,
    "narrator": "আবযা (রাঃ)",
    "bn": "অনুরুপ বর্ণনা করেছেন।",
    "ar": "أَخْبَرَنَا أَحْمَدُ بْنُ سُلَيْمَانَ، قَالَ: حَدَّثَنَا يَحْيَى بْنُ آدَمَ قَالَ: حَدَّثَنَا مَالِكٌ، عَنْ زُبَيْدٍ، عَنْ ذَرٍّ، عَنْ ابْنِ أَبْزَى، مُرْسَلٌ، وَقَدْ رَوَاهُ عَطَاءُ بْنُ السَّائِبِ، عَنْ سَعِيدِ بْنِ عَبْدِ الرَّحْمَنِ بْنِ أَبْزَى، عَنْ أَبِيهِ",
    "grade_id": 1,
    "grade": "নির্ণীত নয়",
    "grade_color": "#F0AD4E",
    "note": null,
    "chapter": {
      "chapter_number": "18"
    }
  }
}