{
  "hadith": {
    "hadith_id": 1927,
    "narrator": "জাফরের পিতা মুহাম্মাদ (রহঃ)",
    "bn": "যে, হাসান ইব্‌ন আলী (রাঃ) বসা ছিলেন, তখন তাঁর কাছ দিয়ে একটি জানাযা নিয়ে যাওয়া হচ্ছিল সেই জানাযা চলে না যাওয়া পর্যন্ত লোকজন দন্ডায়মান ছিল। তখন হাসান (রাঃ) বললেন, একজন ইয়াহুদীর জানাযা নিয়ে যাওয়া হচ্ছিল। তখন রাসূলুল্লাহ্‌ (সাল্লাল্লাহু ‘আলাইহি ওয়া সাল্লাম) তথায় উপবিষ্ট ছিলেন। ইয়াহুদীর জানাযা তাঁর মাথার উপর দিয়ে যাবে তা তিনি অপছন্দ করার কারণে দাঁড়িয়েছিলেন।",
    "ar": "أَخْبَرَنَا إِبْرَاهِيمُ بْنُ هَارُونَ الْبَلْخِيُّ، قَالَ: حَدَّثَنَا حَاتِمٌ، عَنْ جَعْفَرِ بْنِ مُحَمَّدٍ، عَنْ أَبِيهِ، أَنَّ الْحَسَنَ بْنَ عَلِيٍّ كَانَ جَالِسًا فَمُرَّ عَلَيْهِ بِجَنَازَةٍ، فَقَامَ النَّاسُ حَتَّى جَاوَزَتِ الْجَنَازَةُ، فَقَالَ الْحَسَنُ: «إِنَّمَا مُرَّ بِجَنَازَةِ يَهُودِيٍّ وَكَانَ رَسُولُ اللَّهِ صَلَّى اللهُ عَلَيْهِ وَسَلَّمَ عَلَى طَرِيقِهَا جَالِسًا، فَكَرِهَ أَنْ تَعْلُوَ رَأْسَهُ جَنَازَةُ يَهُودِيٍّ، فَقَامَ»",
    "grade_id": 2,
    "grade": "সহিহ হাদিস",
    "grade_color": "#46B891",
    "note": null,
    "chapter": {
      "chapter_number": "19"
    }
  }
}