{
  "hadith": {
    "hadith_id": 2316,
    "narrator": "সালামা ইব্‌ন আকওয়া (রাঃ)",
    "bn": "তিনি বলেন, যখন (আরবী আছে) আয়াত অবর্তীর্ন হল তখন আমাদের মধ্যে যারা ইচ্ছা করত সাওম (রোযা) ভঙ্গ করে ফেলত এবং ফিদয়া দিত। যখন তার পরবর্তী আয়াত: (আরবী আছে) অবর্তীর্ন হল উক্ত আয়াতের হুকুমকে রহিত করে দিল।",
    "ar": "أَخْبَرَنَا قُتَيْبَةُ، قَالَ: أَنْبَأَنَا بَكْرٌ وَهُوَ ابْنُ مُضَرَ، عَنْ عَمْرِو بْنِ الْحَارِثِ، عَنْ بُكَيْرٍ، عَنْ يَزِيدَ، مَوْلَى سَلَمَةَ بْنِ الْأَكْوَعِ، عَنْ سَلَمَةَ بْنِ الْأَكْوَعِ، قَالَ: \" لَمَّا نَزَلَتْ هَذِهِ الْآيَةُ {وَعَلَى الَّذِينَ يُطِيقُونَهُ فِدْيَةٌ طَعَامُ مِسْكِينٍ} [البقرة: 184] كَانَ مَنْ أَرَادَ مِنَّا أَنْ يُفْطِرَ وَيَفْتَدِيَ، حَتَّى نَزَلَتِ الْآيَةُ الَّتِي بَعْدَهَا، فَنَسَخَتْهَا \"",
    "grade_id": 2,
    "grade": "সহিহ হাদিস",
    "grade_color": "#46B891",
    "note": null,
    "chapter": {
      "chapter_number": "20"
    }
  }
}