{
  "hadith": {
    "hadith_id": 2696,
    "narrator": "আয়েশা (রাঃ)",
    "bn": "তিনি বলেনঃ আমি রাসূলুল্লাহ (সাল্লাল্লাহু ‘আলাইহি ওয়া সাল্লাম)-এর মাথার চুলের মূলে সুগন্ধির দীপ্তি দেখছিলাম; অথচ তখন তিনি মুহ্‌রিম ছিলেন।",
    "ar": "أَخْبَرَنَا مَحْمُودُ بْنُ غَيْلَانَ، قَالَ: حَدَّثَنَا أَبُو دَاوُدَ، قَالَ: أَنْبَأَنَا شُعْبَةُ، عَنْ مَنْصُورٍ، عَنْ إِبْرَاهِيمَ، عَنْ الْأَسْوَدِ، عَنْ عَائِشَةَ، قَالَتْ: «كُنْتُ أَنْظُرُ إِلَى وَبِيصِ الطِّيبِ فِي أُصُولِ شَعْرِ رَسُولِ اللَّهِ صَلَّى اللهُ عَلَيْهِ وَسَلَّمَ وَهُوَ مُحْرِمٌ»",
    "grade_id": 2,
    "grade": "সহিহ হাদিস",
    "grade_color": "#46B891",
    "note": null,
    "chapter": {
      "chapter_number": "22"
    }
  }
}