{
  "hadith": {
    "hadith_id": 2752,
    "narrator": "আবূ  হুরায়রা (রাঃ)",
    "bn": "তিনি বলেনঃ নবী করীম (সাল্লাল্লাহু ‘আলাইহি ওয়া সাল্লাম)-এর তালবিয়ার মধ্যে ছিলঃ (হে সত্যের ইলাহ, হাজির আপনার কাছে, হাযির!) আবূ আবদুর রহমান বলেনঃ আবদুল আযীয ব্যতীত আবদুল্লাহ ইবন ফজল থেকে অন্য কেউ এটা বর্ণনা করেছেন বলে জানা নেই। ইসমাঈল ইবন উমাইয়া তাঁর থেকে মুরসালরূপে বর্ণনা করেছেন।",
    "ar": "أَخْبَرَنَا قُتَيْبَةُ، قَالَ: حَدَّثَنَا حُمَيْدُ بْنُ عَبْدِ الرَّحْمَنِ، عَنْ عَبْدِ الْعَزِيزِ بْنِ أَبِي سَلَمَةَ، عَنْ عَبْدِ اللَّهِ بْنِ الْفَضْلِ، عَنْ الْأَعْرَجِ، عَنْ أَبِي هُرَيْرَةَ، قَالَ: «كَانَ مِنْ تَلْبِيَةِ النَّبِيِّ صَلَّى اللهُ عَلَيْهِ وَسَلَّمَ، لَبَّيْكَ إِلَهَ الْحَقِّ» قَالَ أَبُو عَبْدِ الرَّحْمَنِ: لَا أَعْلَمُ أَحَدًا أَسْنَدَ هَذَا، عَنْ عَبْدِ اللَّهِ بْنِ الْفَضْلِ، إِلَّا عَبْدَ الْعَزِيزِ، رَوَاهُ إِسْمَعِيلُ بْنُ أُمَيَّةَ عَنْهُ مُرْسَلًا",
    "grade_id": 2,
    "grade": "সহিহ হাদিস",
    "grade_color": "#46B891",
    "note": null,
    "chapter": {
      "chapter_number": "22"
    }
  }
}