{
  "hadith": {
    "hadith_id": 4479,
    "narrator": "ইব্‌ন উমর (রাঃ)",
    "bn": "রাসূলুল্লাহ (সাল্লাল্লাহু ‘আলাইহি ওয়া সাল্লাম) বলেছেনঃ কোন ক্রেতা ও বিক্রেতার মধ্যকার ক্রয়-বিক্রয় সম্পূর্ণ হয় না, যতক্ষণ না তারা পৃথক হয়ে যায়। তবে ইখতিয়ারের ক্রয়-বিক্রয় ব্যতীত।",
    "ar": "أَخْبَرَنَا عَمْرُو بْنُ يَزِيدَ، عَنْ بَهْزِ بْنِ أَسَدٍ قَالَ: حَدَّثَنَا شُعْبَةُ قَالَ: حَدَّثَنَا عَبْدُ اللَّهِ بْنُ دِينَارٍ، عَنْ ابْنِ عُمَرَ قَالَ: قَالَ رَسُولُ اللَّهِ صَلَّى اللهُ عَلَيْهِ وَسَلَّمَ: «كُلُّ بَيِّعَيْنِ فَلَا بَيْعَ بَيْنَهُمَا حَتَّى يَتَفَرَّقَا إِلَّا بَيْعَ الْخِيَارِ»",
    "grade_id": 2,
    "grade": "সহিহ হাদিস",
    "grade_color": "#46B891",
    "note": null,
    "chapter": {
      "chapter_number": "43"
    }
  }
}