{
  "hadith": {
    "hadith_id": 5020,
    "narrator": "আব্দুল্লাহ ইব্‌ন আমর (রাঃ)",
    "bn": "নবী (সাল্লাল্লাহু ‘আলাইহি ওয়া সাল্লাম) বলেছেনঃ যে ব্যক্তির মধ্যে চারটি অভ্যাস থাকবে, সে মুনাফিক। আর যদি ঐ চারটি অভ্যাসের একটি অভ্যাস থাকে, তবে তার মধ্যে একটি নিফাকের অভ্যাস হলো, যতক্ষণ না তা পরিত্যাগ করেঃ সে যখন কথা বলে, মিথ্যা বলে, কোন ওয়াদা করলে তা খেলাফ করে, যখন কোন অঙ্গীকার করে তা ভঙ্গ করে এবং করো সাথে ঝগড়া করার সময় গালি দেয়।",
    "ar": "أَخْبَرَنَا بِشْرُ بْنُ خَالِدٍ، قَالَ: حَدَّثَنَا مُحَمَّدُ بْنُ جَعْفَرٍ، عَنْ شُعْبَةَ، عَنْ سُلَيْمَانَ، عَنْ عَبْدِ اللَّهِ بْنِ مُرَّةَ، عَنْ مَسْرُوقٍ، عَنْ عَبْدِ اللَّهِ بْنِ عَمْرٍو، عَنِ النَّبِيِّ صَلَّى اللهُ عَلَيْهِ وَسَلَّمَ قَالَ: \" أَرْبَعَةٌ مَنْ كُنَّ فِيهِ كَانَ مُنَافِقًا، أَوْ كَانَتْ فِيهِ خَصْلَةٌ مِنَ الْأَرْبَعِ، كَانَتْ فِيهِ خَصْلَةٌ مِنَ النِّفَاقِ حَتَّى يَدَعَهَا: إِذَا حَدَّثَ كَذَبَ، وَإِذَا وَعَدَ أَخْلَفَ، وَإِذَا عَاهَدَ غَدَرَ، وَإِذَا خَاصَمَ فَجَرَ \"",
    "grade_id": 2,
    "grade": "সহিহ হাদিস",
    "grade_color": "#46B891",
    "note": null,
    "chapter": {
      "chapter_number": "46"
    }
  }
}