{
  "hadith": {
    "hadith_id": 900,
    "narrator": "আবু সাঈদ খুদরী (রাঃ)",
    "bn": "তিনি বলেন, রাসূলুল্লাহ্ (সাল্লাল্লাহু ‘আলাইহি ওয়া সাল্লাম) যখন সালাত আরম্ভ করতেন তখন বলতেনঃ (আরবী)",
    "ar": "أَخْبَرَنَا أَحْمَدُ بْنُ سُلَيْمَانَ، قَالَ: حَدَّثَنَا زَيْدُ بْنُ الْحُبَابِ قَالَ: حَدَّثَنِي جَعْفَرُ بْنُ سُلَيْمَانَ، عَنْ عَلِيِّ بْنُ عَلِيٍّ، عَنْ أَبِي الْمُتَوَكِّلِ، عَنْ أَبِي سَعِيدٍ قَالَ: كَانَ رَسُولُ اللَّهِ صَلَّى اللهُ عَلَيْهِ وَسَلَّمَ إِذَا افْتَتَحَ الصَّلَاةَ قَالَ: «سُبْحَانَكَ اللَّهُمَّ وَبِحَمْدِكَ، وَتَبَارَكَ اسْمُكَ وَتَعَالَى جَدُّكَ وَلَا إِلَهَ غَيْرُكَ»",
    "grade_id": 2,
    "grade": "সহিহ হাদিস",
    "grade_color": "#46B891",
    "note": null,
    "chapter": {
      "chapter_number": "11"
    }
  }
}